pushover/__init__.py
pushover/pushover.py
pushover-0.5.dist-info/METADATA
pushover-0.5.dist-info/WHEEL
pushover-0.5.dist-info/entry_points.txt
pushover-0.5.dist-info/top_level.txt
pushover-0.5.dist-info/RECORD
